{
  "trust_code": "RP5",
  "trust_name": "Doncaster and Bassetlaw Teaching Hospitals NHS Foundation Trust",
  "region": "North East and Yorkshire",
  "lat": 53.7042,
  "lng": -1.5597,
  "imd_score": 40.6,
  "is_teaching": true,
  "scorecard": {
    "avg_wait_minutes": 169,
    "breach_rate_pct": 27.1,
    "busiest_month": "July",
    "busiest_day": "Monday",
    "total_annual_attendances": 33896,
    "national_rank": 109,
    "national_total": 159,
    "vs_national_avg_pct": 5.7
  },
  "monthly_data": [
    {
      "year": 2020,
      "month": 4,
      "attendances": 8175,
      "breach_rate": 9.1,
      "avg_temp": 7.9,
      "flu_rate": 0.3
    },
    {
      "year": 2020,
      "month": 5,
      "attendances": 11491,
      "breach_rate": 5.3,
      "avg_temp": 9.6,
      "flu_rate": 0.1
    },
    {
      "year": 2020,
      "month": 6,
      "attendances": 12733,
      "breach_rate": 6.8,
      "avg_temp": 14.6,
      "flu_rate": 0.0
    },
    {
      "year": 2020,
      "month": 7,
      "attendances": 13846,
      "breach_rate": 8.1,
      "avg_temp": 15.1,
      "flu_rate": 0.0
    },
    {
      "year": 2020,
      "month": 8,
      "attendances": 14836,
      "breach_rate": 11.3,
      "avg_temp": 18.1,
      "flu_rate": 0.0
    },
    {
      "year": 2020,
      "month": 9,
      "attendances": 14939,
      "breach_rate": 17.4,
      "avg_temp": 13.8,
      "flu_rate": 0.0
    },
    {
      "year": 2020,
      "month": 10,
      "attendances": 13015,
      "breach_rate": 24.0,
      "avg_temp": 10.8,
      "flu_rate": 0.2
    },
    {
      "year": 2020,
      "month": 11,
      "attendances": 11527,
      "breach_rate": 23.2,
      "avg_temp": 5.7,
      "flu_rate": 0.7
    },
    {
      "year": 2020,
      "month": 12,
      "attendances": 12168,
      "breach_rate": 20.8,
      "avg_temp": 2.6,
      "flu_rate": 1.0
    },
    {
      "year": 2021,
      "month": 1,
      "attendances": 11319,
      "breach_rate": 19.3,
      "avg_temp": 4.7,
      "flu_rate": 2.1
    },
    {
      "year": 2021,
      "month": 2,
      "attendances": 11025,
      "breach_rate": 19.7,
      "avg_temp": 3.7,
      "flu_rate": 1.5
    },
    {
      "year": 2021,
      "month": 3,
      "attendances": 14443,
      "breach_rate": 15.7,
      "avg_temp": 6.2,
      "flu_rate": 1.1
    },
    {
      "year": 2021,
      "month": 4,
      "attendances": 15824,
      "breach_rate": 16.9,
      "avg_temp": 8.2,
      "flu_rate": 0.3
    },
    {
      "year": 2021,
      "month": 5,
      "attendances": 16819,
      "breach_rate": 19.7,
      "avg_temp": 13.0,
      "flu_rate": 0.1
    },
    {
      "year": 2021,
      "month": 6,
      "attendances": 17551,
      "breach_rate": 21.9,
      "avg_temp": 13.8,
      "flu_rate": 0.1
    },
    {
      "year": 2021,
      "month": 7,
      "attendances": 17532,
      "breach_rate": 26.5,
      "avg_temp": 15.2,
      "flu_rate": 0.1
    },
    {
      "year": 2021,
      "month": 8,
      "attendances": 16478,
      "breach_rate": 27.5,
      "avg_temp": 16.6,
      "flu_rate": 0.1
    },
    {
      "year": 2021,
      "month": 9,
      "attendances": 17350,
      "breach_rate": 28.0,
      "avg_temp": 14.6,
      "flu_rate": 0.6
    },
    {
      "year": 2021,
      "month": 10,
      "attendances": 16535,
      "breach_rate": 29.5,
      "avg_temp": 11.3,
      "flu_rate": 1.9
    },
    {
      "year": 2021,
      "month": 11,
      "attendances": 15892,
      "breach_rate": 30.0,
      "avg_temp": 6.9,
      "flu_rate": 3.5
    },
    {
      "year": 2021,
      "month": 12,
      "attendances": 14639,
      "breach_rate": 31.7,
      "avg_temp": 4.2,
      "flu_rate": 9.1
    },
    {
      "year": 2022,
      "month": 1,
      "attendances": 14814,
      "breach_rate": 31.8,
      "avg_temp": 5.3,
      "flu_rate": 12.8
    },
    {
      "year": 2022,
      "month": 2,
      "attendances": 14402,
      "breach_rate": 29.1,
      "avg_temp": 2.4,
      "flu_rate": 10.7
    },
    {
      "year": 2022,
      "month": 3,
      "attendances": 17185,
      "breach_rate": 29.6,
      "avg_temp": 3.6,
      "flu_rate": 5.2
    },
    {
      "year": 2022,
      "month": 4,
      "attendances": 15836,
      "breach_rate": 28.5,
      "avg_temp": 8.1,
      "flu_rate": 2.4
    },
    {
      "year": 2022,
      "month": 5,
      "attendances": 17663,
      "breach_rate": 30.0,
      "avg_temp": 10.2,
      "flu_rate": 0.4
    },
    {
      "year": 2022,
      "month": 6,
      "attendances": 17119,
      "breach_rate": 30.0,
      "avg_temp": 12.1,
      "flu_rate": 0.2
    },
    {
      "year": 2022,
      "month": 7,
      "attendances": 17247,
      "breach_rate": 29.2,
      "avg_temp": 14.5,
      "flu_rate": 0.1
    },
    {
      "year": 2022,
      "month": 8,
      "attendances": 16114,
      "breach_rate": 31.6,
      "avg_temp": 15.9,
      "flu_rate": 0.1
    },
    {
      "year": 2022,
      "month": 9,
      "attendances": 15648,
      "breach_rate": 30.6,
      "avg_temp": 13.8,
      "flu_rate": 0.6
    },
    {
      "year": 2022,
      "month": 10,
      "attendances": 16223,
      "breach_rate": 32.0,
      "avg_temp": 9.8,
      "flu_rate": 3.0
    },
    {
      "year": 2022,
      "month": 11,
      "attendances": 16224,
      "breach_rate": 33.6,
      "avg_temp": 4.5,
      "flu_rate": 8.0
    },
    {
      "year": 2022,
      "month": 12,
      "attendances": 16997,
      "breach_rate": 39.4,
      "avg_temp": 4.7,
      "flu_rate": 16.1
    },
    {
      "year": 2023,
      "month": 1,
      "attendances": 14903,
      "breach_rate": 34.8,
      "avg_temp": 2.0,
      "flu_rate": 16.7
    },
    {
      "year": 2023,
      "month": 2,
      "attendances": 14090,
      "breach_rate": 31.0,
      "avg_temp": 4.9,
      "flu_rate": 6.7
    },
    {
      "year": 2023,
      "month": 3,
      "attendances": 15915,
      "breach_rate": 34.5,
      "avg_temp": 6.5,
      "flu_rate": 8.6
    },
    {
      "year": 2023,
      "month": 4,
      "attendances": 15280,
      "breach_rate": 31.8,
      "avg_temp": 9.8,
      "flu_rate": 2.0
    },
    {
      "year": 2023,
      "month": 5,
      "attendances": 16992,
      "breach_rate": 25.8,
      "avg_temp": 12.1,
      "flu_rate": 0.5
    },
    {
      "year": 2023,
      "month": 6,
      "attendances": 17094,
      "breach_rate": 30.3,
      "avg_temp": 13.4,
      "flu_rate": 0.3
    },
    {
      "year": 2023,
      "month": 7,
      "attendances": 17245,
      "breach_rate": 31.8,
      "avg_temp": 18.4,
      "flu_rate": 0.1
    },
    {
      "year": 2023,
      "month": 8,
      "attendances": 16332,
      "breach_rate": 32.0,
      "avg_temp": 14.6,
      "flu_rate": 0.1
    },
    {
      "year": 2023,
      "month": 9,
      "attendances": 16370,
      "breach_rate": 30.6,
      "avg_temp": 15.5,
      "flu_rate": 0.5
    },
    {
      "year": 2023,
      "month": 10,
      "attendances": 16559,
      "breach_rate": 36.7,
      "avg_temp": 9.0,
      "flu_rate": 2.0
    },
    {
      "year": 2023,
      "month": 11,
      "attendances": 16282,
      "breach_rate": 33.8,
      "avg_temp": 7.9,
      "flu_rate": 4.3
    },
    {
      "year": 2023,
      "month": 12,
      "attendances": 16333,
      "breach_rate": 37.5,
      "avg_temp": 3.2,
      "flu_rate": 9.2
    },
    {
      "year": 2024,
      "month": 1,
      "attendances": 16964,
      "breach_rate": 38.3,
      "avg_temp": 2.9,
      "flu_rate": 12.7
    },
    {
      "year": 2024,
      "month": 2,
      "attendances": 16148,
      "breach_rate": 34.1,
      "avg_temp": 2.3,
      "flu_rate": 10.0
    },
    {
      "year": 2024,
      "month": 3,
      "attendances": 17164,
      "breach_rate": 23.9,
      "avg_temp": 6.6,
      "flu_rate": 4.3
    },
    {
      "year": 2024,
      "month": 4,
      "attendances": 16082,
      "breach_rate": 25.5,
      "avg_temp": 8.5,
      "flu_rate": 1.9
    },
    {
      "year": 2024,
      "month": 5,
      "attendances": 18090,
      "breach_rate": 27.4,
      "avg_temp": 11.3,
      "flu_rate": 0.5
    },
    {
      "year": 2024,
      "month": 6,
      "attendances": 17475,
      "breach_rate": 26.6,
      "avg_temp": 16.3,
      "flu_rate": 0.3
    },
    {
      "year": 2024,
      "month": 7,
      "attendances": 17963,
      "breach_rate": 30.2,
      "avg_temp": 15.1,
      "flu_rate": 0.1
    },
    {
      "year": 2024,
      "month": 8,
      "attendances": 16496,
      "breach_rate": 27.5,
      "avg_temp": 16.2,
      "flu_rate": 0.1
    },
    {
      "year": 2024,
      "month": 9,
      "attendances": 16947,
      "breach_rate": 30.3,
      "avg_temp": 14.2,
      "flu_rate": 0.5
    },
    {
      "year": 2024,
      "month": 10,
      "attendances": 17663,
      "breach_rate": 29.7,
      "avg_temp": 12.6,
      "flu_rate": 1.9
    },
    {
      "year": 2024,
      "month": 11,
      "attendances": 17516,
      "breach_rate": 27.1,
      "avg_temp": 8.9,
      "flu_rate": 5.0
    },
    {
      "year": 2024,
      "month": 12,
      "attendances": 17876,
      "breach_rate": 30.0,
      "avg_temp": 6.9,
      "flu_rate": 12.3
    },
    {
      "year": 2025,
      "month": 1,
      "attendances": 17076,
      "breach_rate": 30.1,
      "avg_temp": 4.5,
      "flu_rate": 13.9
    },
    {
      "year": 2025,
      "month": 2,
      "attendances": 16043,
      "breach_rate": 27.6,
      "avg_temp": 2.4,
      "flu_rate": 12.8
    },
    {
      "year": 2025,
      "month": 3,
      "attendances": 18457,
      "breach_rate": 25.3,
      "avg_temp": 6.1,
      "flu_rate": 6.7
    },
    {
      "year": 2025,
      "month": 4,
      "attendances": 17990,
      "breach_rate": 26.4,
      "avg_temp": 9.3,
      "flu_rate": 1.6
    },
    {
      "year": 2025,
      "month": 5,
      "attendances": 18317,
      "breach_rate": 26.0,
      "avg_temp": 14.4,
      "flu_rate": 0.5
    },
    {
      "year": 2025,
      "month": 6,
      "attendances": 18583,
      "breach_rate": 24.4,
      "avg_temp": 14.7,
      "flu_rate": 0.1
    },
    {
      "year": 2025,
      "month": 7,
      "attendances": 18807,
      "breach_rate": 26.1,
      "avg_temp": 15.3,
      "flu_rate": 0.1
    },
    {
      "year": 2025,
      "month": 8,
      "attendances": 17831,
      "breach_rate": 27.2,
      "avg_temp": 14.9,
      "flu_rate": 0.1
    },
    {
      "year": 2025,
      "month": 9,
      "attendances": 17953,
      "breach_rate": 30.2,
      "avg_temp": 13.0,
      "flu_rate": 0.4
    },
    {
      "year": 2025,
      "month": 10,
      "attendances": 18147,
      "breach_rate": 30.6,
      "avg_temp": 9.6,
      "flu_rate": 2.3
    },
    {
      "year": 2025,
      "month": 11,
      "attendances": 17649,
      "breach_rate": 29.2,
      "avg_temp": 4.8,
      "flu_rate": 5.2
    },
    {
      "year": 2025,
      "month": 12,
      "attendances": 17275,
      "breach_rate": 30.9,
      "avg_temp": 3.5,
      "flu_rate": 6.8
    },
    {
      "year": 2026,
      "month": 1,
      "attendances": 17819,
      "breach_rate": 32.1,
      "avg_temp": 4.8,
      "flu_rate": 12.6
    },
    {
      "year": 2026,
      "month": 2,
      "attendances": 16077,
      "breach_rate": 29.4,
      "avg_temp": 5.1,
      "flu_rate": 7.5
    }
  ],
  "compliance_trend": [
    {
      "year": 2020,
      "month": 4,
      "compliance_pct": 90.9,
      "national_avg": 92.9
    },
    {
      "year": 2020,
      "month": 5,
      "compliance_pct": 94.7,
      "national_avg": 95.0
    },
    {
      "year": 2020,
      "month": 6,
      "compliance_pct": 93.2,
      "national_avg": 94.4
    },
    {
      "year": 2020,
      "month": 7,
      "compliance_pct": 91.9,
      "national_avg": 93.8
    },
    {
      "year": 2020,
      "month": 8,
      "compliance_pct": 88.7,
      "national_avg": 91.4
    },
    {
      "year": 2020,
      "month": 9,
      "compliance_pct": 82.6,
      "national_avg": 89.9
    },
    {
      "year": 2020,
      "month": 10,
      "compliance_pct": 76.0,
      "national_avg": 87.9
    },
    {
      "year": 2020,
      "month": 11,
      "compliance_pct": 76.8,
      "national_avg": 87.4
    },
    {
      "year": 2020,
      "month": 12,
      "compliance_pct": 79.2,
      "national_avg": 84.6
    },
    {
      "year": 2021,
      "month": 1,
      "compliance_pct": 80.7,
      "national_avg": 83.4
    },
    {
      "year": 2021,
      "month": 2,
      "compliance_pct": 80.3,
      "national_avg": 87.4
    },
    {
      "year": 2021,
      "month": 3,
      "compliance_pct": 84.3,
      "national_avg": 89.1
    },
    {
      "year": 2021,
      "month": 4,
      "compliance_pct": 83.1,
      "national_avg": 88.3
    },
    {
      "year": 2021,
      "month": 5,
      "compliance_pct": 80.3,
      "national_avg": 86.9
    },
    {
      "year": 2021,
      "month": 6,
      "compliance_pct": 78.1,
      "national_avg": 84.9
    },
    {
      "year": 2021,
      "month": 7,
      "compliance_pct": 73.5,
      "national_avg": 81.7
    },
    {
      "year": 2021,
      "month": 8,
      "compliance_pct": 72.5,
      "national_avg": 81.1
    },
    {
      "year": 2021,
      "month": 9,
      "compliance_pct": 72.0,
      "national_avg": 79.6
    },
    {
      "year": 2021,
      "month": 10,
      "compliance_pct": 70.5,
      "national_avg": 78.5
    },
    {
      "year": 2021,
      "month": 11,
      "compliance_pct": 70.0,
      "national_avg": 78.7
    },
    {
      "year": 2021,
      "month": 12,
      "compliance_pct": 68.3,
      "national_avg": 78.2
    },
    {
      "year": 2022,
      "month": 1,
      "compliance_pct": 68.2,
      "national_avg": 79.1
    },
    {
      "year": 2022,
      "month": 2,
      "compliance_pct": 70.9,
      "national_avg": 78.1
    },
    {
      "year": 2022,
      "month": 3,
      "compliance_pct": 70.4,
      "national_avg": 76.6
    },
    {
      "year": 2022,
      "month": 4,
      "compliance_pct": 71.5,
      "national_avg": 76.7
    },
    {
      "year": 2022,
      "month": 5,
      "compliance_pct": 70.0,
      "national_avg": 77.5
    },
    {
      "year": 2022,
      "month": 6,
      "compliance_pct": 70.0,
      "national_avg": 76.7
    },
    {
      "year": 2022,
      "month": 7,
      "compliance_pct": 70.8,
      "national_avg": 75.7
    },
    {
      "year": 2022,
      "month": 8,
      "compliance_pct": 68.4,
      "national_avg": 76.2
    },
    {
      "year": 2022,
      "month": 9,
      "compliance_pct": 69.4,
      "national_avg": 75.8
    },
    {
      "year": 2022,
      "month": 10,
      "compliance_pct": 68.0,
      "national_avg": 74.5
    },
    {
      "year": 2022,
      "month": 11,
      "compliance_pct": 66.4,
      "national_avg": 74.0
    },
    {
      "year": 2022,
      "month": 12,
      "compliance_pct": 60.6,
      "national_avg": 70.2
    },
    {
      "year": 2023,
      "month": 1,
      "compliance_pct": 65.2,
      "national_avg": 76.6
    },
    {
      "year": 2023,
      "month": 2,
      "compliance_pct": 69.0,
      "national_avg": 75.8
    },
    {
      "year": 2023,
      "month": 3,
      "compliance_pct": 65.5,
      "national_avg": 75.9
    },
    {
      "year": 2023,
      "month": 4,
      "compliance_pct": 68.2,
      "national_avg": 78.5
    },
    {
      "year": 2023,
      "month": 5,
      "compliance_pct": 74.2,
      "national_avg": 77.9
    },
    {
      "year": 2023,
      "month": 6,
      "compliance_pct": 69.7,
      "national_avg": 74.9
    },
    {
      "year": 2023,
      "month": 7,
      "compliance_pct": 68.2,
      "national_avg": 75.5
    },
    {
      "year": 2023,
      "month": 8,
      "compliance_pct": 68.0,
      "national_avg": 74.6
    },
    {
      "year": 2023,
      "month": 9,
      "compliance_pct": 69.4,
      "national_avg": 73.2
    },
    {
      "year": 2023,
      "month": 10,
      "compliance_pct": 63.3,
      "national_avg": 71.7
    },
    {
      "year": 2023,
      "month": 11,
      "compliance_pct": 66.2,
      "national_avg": 71.3
    },
    {
      "year": 2023,
      "month": 12,
      "compliance_pct": 62.5,
      "national_avg": 70.9
    },
    {
      "year": 2024,
      "month": 1,
      "compliance_pct": 61.7,
      "national_avg": 71.6
    },
    {
      "year": 2024,
      "month": 2,
      "compliance_pct": 65.9,
      "national_avg": 72.5
    },
    {
      "year": 2024,
      "month": 3,
      "compliance_pct": 76.1,
      "national_avg": 75.5
    },
    {
      "year": 2024,
      "month": 4,
      "compliance_pct": 74.5,
      "national_avg": 75.9
    },
    {
      "year": 2024,
      "month": 5,
      "compliance_pct": 72.6,
      "national_avg": 75.3
    },
    {
      "year": 2024,
      "month": 6,
      "compliance_pct": 73.4,
      "national_avg": 75.9
    },
    {
      "year": 2024,
      "month": 7,
      "compliance_pct": 69.8,
      "national_avg": 76.6
    },
    {
      "year": 2024,
      "month": 8,
      "compliance_pct": 72.5,
      "national_avg": 77.6
    },
    {
      "year": 2024,
      "month": 9,
      "compliance_pct": 69.7,
      "national_avg": 75.6
    },
    {
      "year": 2024,
      "month": 10,
      "compliance_pct": 70.3,
      "national_avg": 74.3
    },
    {
      "year": 2024,
      "month": 11,
      "compliance_pct": 72.9,
      "national_avg": 73.6
    },
    {
      "year": 2024,
      "month": 12,
      "compliance_pct": 70.0,
      "national_avg": 72.2
    },
    {
      "year": 2025,
      "month": 1,
      "compliance_pct": 69.9,
      "national_avg": 74.2
    },
    {
      "year": 2025,
      "month": 2,
      "compliance_pct": 72.4,
      "national_avg": 74.7
    },
    {
      "year": 2025,
      "month": 3,
      "compliance_pct": 74.7,
      "national_avg": 76.1
    },
    {
      "year": 2025,
      "month": 4,
      "compliance_pct": 73.6,
      "national_avg": 76.0
    },
    {
      "year": 2025,
      "month": 5,
      "compliance_pct": 74.0,
      "national_avg": 76.4
    },
    {
      "year": 2025,
      "month": 6,
      "compliance_pct": 75.6,
      "national_avg": 76.6
    },
    {
      "year": 2025,
      "month": 7,
      "compliance_pct": 73.9,
      "national_avg": 77.3
    },
    {
      "year": 2025,
      "month": 8,
      "compliance_pct": 72.8,
      "national_avg": 77.2
    },
    {
      "year": 2025,
      "month": 9,
      "compliance_pct": 69.8,
      "national_avg": 76.4
    },
    {
      "year": 2025,
      "month": 10,
      "compliance_pct": 69.4,
      "national_avg": 75.4
    },
    {
      "year": 2025,
      "month": 11,
      "compliance_pct": 70.8,
      "national_avg": 75.7
    },
    {
      "year": 2025,
      "month": 12,
      "compliance_pct": 69.1,
      "national_avg": 75.3
    },
    {
      "year": 2026,
      "month": 1,
      "compliance_pct": 67.9,
      "national_avg": 73.9
    },
    {
      "year": 2026,
      "month": 2,
      "compliance_pct": 70.6,
      "national_avg": 75.4
    }
  ],
  "heatmap": {
    "rows": [
      "Mon",
      "Tue",
      "Wed",
      "Thu",
      "Fri",
      "Sat",
      "Sun"
    ],
    "cols": [
      1,
      2,
      3,
      4,
      5,
      6,
      7,
      8,
      9,
      10,
      11,
      12
    ],
    "values": [
      [
        570,
        539,
        613,
        548,
        610,
        617,
        630,
        602,
        609,
        603,
        584,
        585
      ],
      [
        550,
        520,
        591,
        528,
        588,
        595,
        608,
        581,
        587,
        581,
        563,
        564
      ],
      [
        535,
        505,
        574,
        513,
        572,
        579,
        591,
        565,
        571,
        565,
        547,
        549
      ],
      [
        525,
        496,
        564,
        504,
        561,
        568,
        580,
        554,
        560,
        554,
        537,
        538
      ],
      [
        509,
        481,
        547,
        489,
        545,
        551,
        563,
        538,
        544,
        538,
        521,
        522
      ],
      [
        448,
        424,
        481,
        430,
        479,
        485,
        495,
        473,
        479,
        473,
        459,
        460
      ],
      [
        428,
        404,
        460,
        411,
        458,
        463,
        473,
        452,
        457,
        452,
        438,
        439
      ]
    ]
  },
  "seasonal_decomposition": {
    "dates": [
      "2020-04",
      "2020-05",
      "2020-06",
      "2020-07",
      "2020-08",
      "2020-09",
      "2020-10",
      "2020-11",
      "2020-12",
      "2021-01",
      "2021-02",
      "2021-03",
      "2021-04",
      "2021-05",
      "2021-06",
      "2021-07",
      "2021-08",
      "2021-09",
      "2021-10",
      "2021-11",
      "2021-12",
      "2022-01",
      "2022-02",
      "2022-03",
      "2022-04",
      "2022-05",
      "2022-06",
      "2022-07",
      "2022-08",
      "2022-09",
      "2022-10",
      "2022-11",
      "2022-12",
      "2023-01",
      "2023-02",
      "2023-03",
      "2023-04",
      "2023-05",
      "2023-06",
      "2023-07",
      "2023-08",
      "2023-09",
      "2023-10",
      "2023-11",
      "2023-12",
      "2024-01",
      "2024-02",
      "2024-03",
      "2024-04",
      "2024-05",
      "2024-06",
      "2024-07",
      "2024-08",
      "2024-09",
      "2024-10",
      "2024-11",
      "2024-12",
      "2025-01",
      "2025-02",
      "2025-03",
      "2025-04",
      "2025-05",
      "2025-06",
      "2025-07",
      "2025-08",
      "2025-09",
      "2025-10",
      "2025-11",
      "2025-12",
      "2026-01",
      "2026-02"
    ],
    "trend": [
      null,
      null,
      null,
      null,
      null,
      null,
      12778.5,
      13319.2,
      13741.9,
      14096.2,
      14318.2,
      14487.1,
      14734.2,
      15062.8,
      15347.6,
      15596.2,
      15882.5,
      16137.5,
      16252.2,
      16287.9,
      16305.1,
      16275.2,
      16248.2,
      16162.1,
      16078.2,
      16079.0,
      16191.1,
      16293.0,
      16283.8,
      16217.8,
      16141.8,
      16090.6,
      16061.6,
      16060.5,
      16069.5,
      16108.7,
      16152.8,
      16169.2,
      16143.9,
      16202.1,
      16373.7,
      16511.5,
      16597.0,
      16676.2,
      16737.8,
      16783.6,
      16820.3,
      16851.2,
      16921.2,
      17018.7,
      17134.4,
      17203.3,
      17203.6,
      17253.1,
      17386.5,
      17475.5,
      17531.1,
      17612.4,
      17703.2,
      17800.8,
      17862.8,
      17888.5,
      17869.0,
      17875.0,
      17907.3,
      null,
      null,
      null,
      null,
      null,
      null
    ],
    "seasonal": [
      -116.6,
      1163.5,
      1058.1,
      1155.8,
      -49.1,
      79.6,
      198.7,
      -450.8,
      -442.0,
      -1119.5,
      -1859.4,
      381.7,
      -116.6,
      1163.5,
      1058.1,
      1155.8,
      -49.1,
      79.6,
      198.7,
      -450.8,
      -442.0,
      -1119.5,
      -1859.4,
      381.7,
      -116.6,
      1163.5,
      1058.1,
      1155.8,
      -49.1,
      79.6,
      198.7,
      -450.8,
      -442.0,
      -1119.5,
      -1859.4,
      381.7,
      -116.6,
      1163.5,
      1058.1,
      1155.8,
      -49.1,
      79.6,
      198.7,
      -450.8,
      -442.0,
      -1119.5,
      -1859.4,
      381.7,
      -116.6,
      1163.5,
      1058.1,
      1155.8,
      -49.1,
      79.6,
      198.7,
      -450.8,
      -442.0,
      -1119.5,
      -1859.4,
      381.7,
      -116.6,
      1163.5,
      1058.1,
      1155.8,
      -49.1,
      79.6,
      198.7,
      -450.8,
      -442.0,
      -1119.5,
      -1859.4
    ],
    "residual": [
      null,
      null,
      null,
      null,
      null,
      null,
      37.8,
      -1341.4,
      -1131.9,
      -1657.7,
      -1433.8,
      -425.8,
      1206.3,
      592.8,
      1145.3,
      780.0,
      644.6,
      1132.9,
      84.1,
      54.9,
      -1224.1,
      -341.7,
      13.2,
      641.2,
      -125.6,
      420.5,
      -130.2,
      -201.8,
      -120.6,
      -649.5,
      -117.4,
      584.2,
      1377.4,
      -38.0,
      -120.1,
      -575.4,
      -756.2,
      -340.6,
      -108.0,
      -112.9,
      7.4,
      -221.2,
      -236.7,
      56.6,
      37.2,
      1299.9,
      1187.1,
      -68.9,
      -722.7,
      -92.1,
      -717.5,
      -396.1,
      -658.5,
      -385.8,
      77.8,
      491.3,
      786.9,
      583.1,
      199.2,
      274.5,
      243.7,
      -735.0,
      -344.1,
      -223.7,
      -27.2,
      null,
      null,
      null,
      null,
      null,
      null
    ]
  },
  "weather_correlation": {
    "points": [
      {
        "temp": 7.9,
        "attendances": 8175
      },
      {
        "temp": 9.6,
        "attendances": 11491
      },
      {
        "temp": 14.6,
        "attendances": 12733
      },
      {
        "temp": 15.1,
        "attendances": 13846
      },
      {
        "temp": 18.1,
        "attendances": 14836
      },
      {
        "temp": 13.8,
        "attendances": 14939
      },
      {
        "temp": 10.8,
        "attendances": 13015
      },
      {
        "temp": 5.7,
        "attendances": 11527
      },
      {
        "temp": 2.6,
        "attendances": 12168
      },
      {
        "temp": 4.7,
        "attendances": 11319
      },
      {
        "temp": 3.7,
        "attendances": 11025
      },
      {
        "temp": 6.2,
        "attendances": 14443
      },
      {
        "temp": 8.2,
        "attendances": 15824
      },
      {
        "temp": 13.0,
        "attendances": 16819
      },
      {
        "temp": 13.8,
        "attendances": 17551
      },
      {
        "temp": 15.2,
        "attendances": 17532
      },
      {
        "temp": 16.6,
        "attendances": 16478
      },
      {
        "temp": 14.6,
        "attendances": 17350
      },
      {
        "temp": 11.3,
        "attendances": 16535
      },
      {
        "temp": 6.9,
        "attendances": 15892
      },
      {
        "temp": 4.2,
        "attendances": 14639
      },
      {
        "temp": 5.3,
        "attendances": 14814
      },
      {
        "temp": 2.4,
        "attendances": 14402
      },
      {
        "temp": 3.6,
        "attendances": 17185
      },
      {
        "temp": 8.1,
        "attendances": 15836
      },
      {
        "temp": 10.2,
        "attendances": 17663
      },
      {
        "temp": 12.1,
        "attendances": 17119
      },
      {
        "temp": 14.5,
        "attendances": 17247
      },
      {
        "temp": 15.9,
        "attendances": 16114
      },
      {
        "temp": 13.8,
        "attendances": 15648
      },
      {
        "temp": 9.8,
        "attendances": 16223
      },
      {
        "temp": 4.5,
        "attendances": 16224
      },
      {
        "temp": 4.7,
        "attendances": 16997
      },
      {
        "temp": 2.0,
        "attendances": 14903
      },
      {
        "temp": 4.9,
        "attendances": 14090
      },
      {
        "temp": 6.5,
        "attendances": 15915
      },
      {
        "temp": 9.8,
        "attendances": 15280
      },
      {
        "temp": 12.1,
        "attendances": 16992
      },
      {
        "temp": 13.4,
        "attendances": 17094
      },
      {
        "temp": 18.4,
        "attendances": 17245
      },
      {
        "temp": 14.6,
        "attendances": 16332
      },
      {
        "temp": 15.5,
        "attendances": 16370
      },
      {
        "temp": 9.0,
        "attendances": 16559
      },
      {
        "temp": 7.9,
        "attendances": 16282
      },
      {
        "temp": 3.2,
        "attendances": 16333
      },
      {
        "temp": 2.9,
        "attendances": 16964
      },
      {
        "temp": 2.3,
        "attendances": 16148
      },
      {
        "temp": 6.6,
        "attendances": 17164
      },
      {
        "temp": 8.5,
        "attendances": 16082
      },
      {
        "temp": 11.3,
        "attendances": 18090
      },
      {
        "temp": 16.3,
        "attendances": 17475
      },
      {
        "temp": 15.1,
        "attendances": 17963
      },
      {
        "temp": 16.2,
        "attendances": 16496
      },
      {
        "temp": 14.2,
        "attendances": 16947
      },
      {
        "temp": 12.6,
        "attendances": 17663
      },
      {
        "temp": 8.9,
        "attendances": 17516
      },
      {
        "temp": 6.9,
        "attendances": 17876
      },
      {
        "temp": 4.5,
        "attendances": 17076
      },
      {
        "temp": 2.4,
        "attendances": 16043
      },
      {
        "temp": 6.1,
        "attendances": 18457
      },
      {
        "temp": 9.3,
        "attendances": 17990
      },
      {
        "temp": 14.4,
        "attendances": 18317
      },
      {
        "temp": 14.7,
        "attendances": 18583
      },
      {
        "temp": 15.3,
        "attendances": 18807
      },
      {
        "temp": 14.9,
        "attendances": 17831
      },
      {
        "temp": 13.0,
        "attendances": 17953
      },
      {
        "temp": 9.6,
        "attendances": 18147
      },
      {
        "temp": 4.8,
        "attendances": 17649
      },
      {
        "temp": 3.5,
        "attendances": 17275
      },
      {
        "temp": 4.8,
        "attendances": 17819
      },
      {
        "temp": 5.1,
        "attendances": 16077
      }
    ],
    "correlation_r": 0.279,
    "trendline": {
      "slope": 120.8,
      "intercept": 14914.0
    }
  },
  "bank_holiday_impact": {
    "before": 550,
    "during": 481,
    "after": 560
  },
  "predictions_grid": {
    "months": [
      1,
      2,
      3,
      4,
      5,
      6,
      7,
      8,
      9,
      10,
      11,
      12
    ],
    "temp_buckets": [
      -5,
      0,
      5,
      10,
      15,
      20,
      25,
      30
    ],
    "values": {
      "1": {
        "-5": 15737,
        "0": 15737,
        "5": 15737,
        "10": 15765,
        "15": 15765,
        "20": 15765,
        "25": 15765,
        "30": 15765
      },
      "2": {
        "-5": 15666,
        "0": 15666,
        "5": 15666,
        "10": 15685,
        "15": 15685,
        "20": 15685,
        "25": 15685,
        "30": 15685
      },
      "3": {
        "-5": 17878,
        "0": 17878,
        "5": 17878,
        "10": 17914,
        "15": 17909,
        "20": 17909,
        "25": 17909,
        "30": 17909
      },
      "4": {
        "-5": 16534,
        "0": 16534,
        "5": 16534,
        "10": 16562,
        "15": 16559,
        "20": 16559,
        "25": 16559,
        "30": 16559
      },
      "5": {
        "-5": 17241,
        "0": 17241,
        "5": 17241,
        "10": 17269,
        "15": 17263,
        "20": 17263,
        "25": 17263,
        "30": 17263
      },
      "6": {
        "-5": 17030,
        "0": 17030,
        "5": 17030,
        "10": 17058,
        "15": 17052,
        "20": 17052,
        "25": 17052,
        "30": 17052
      },
      "7": {
        "-5": 17021,
        "0": 17021,
        "5": 17021,
        "10": 17049,
        "15": 17043,
        "20": 17043,
        "25": 17043,
        "30": 17043
      },
      "8": {
        "-5": 16988,
        "0": 16988,
        "5": 16988,
        "10": 17016,
        "15": 17013,
        "20": 17013,
        "25": 17013,
        "30": 17013
      },
      "9": {
        "-5": 16879,
        "0": 16879,
        "5": 16879,
        "10": 16907,
        "15": 16904,
        "20": 16904,
        "25": 16904,
        "30": 16904
      },
      "10": {
        "-5": 17066,
        "0": 17066,
        "5": 17066,
        "10": 17094,
        "15": 17089,
        "20": 17089,
        "25": 17089,
        "30": 17089
      },
      "11": {
        "-5": 16521,
        "0": 16521,
        "5": 16521,
        "10": 16549,
        "15": 16549,
        "20": 16549,
        "25": 16549,
        "30": 16549
      },
      "12": {
        "-5": 16530,
        "0": 16530,
        "5": 16530,
        "10": 16558,
        "15": 16558,
        "20": 16558,
        "25": 16558,
        "30": 16558
      }
    },
    "confidence_intervals": {
      "1": {
        "-5": {
          "low": 13848,
          "high": 17625
        },
        "0": {
          "low": 13848,
          "high": 17625
        },
        "5": {
          "low": 13848,
          "high": 17625
        },
        "10": {
          "low": 13873,
          "high": 17657
        },
        "15": {
          "low": 13873,
          "high": 17657
        },
        "20": {
          "low": 13873,
          "high": 17657
        },
        "25": {
          "low": 13873,
          "high": 17657
        },
        "30": {
          "low": 13873,
          "high": 17657
        }
      },
      "2": {
        "-5": {
          "low": 13786,
          "high": 17545
        },
        "0": {
          "low": 13786,
          "high": 17545
        },
        "5": {
          "low": 13786,
          "high": 17545
        },
        "10": {
          "low": 13803,
          "high": 17568
        },
        "15": {
          "low": 13803,
          "high": 17568
        },
        "20": {
          "low": 13803,
          "high": 17568
        },
        "25": {
          "low": 13803,
          "high": 17568
        },
        "30": {
          "low": 13803,
          "high": 17568
        }
      },
      "3": {
        "-5": {
          "low": 15733,
          "high": 20024
        },
        "0": {
          "low": 15733,
          "high": 20024
        },
        "5": {
          "low": 15733,
          "high": 20024
        },
        "10": {
          "low": 15765,
          "high": 20064
        },
        "15": {
          "low": 15760,
          "high": 20058
        },
        "20": {
          "low": 15760,
          "high": 20058
        },
        "25": {
          "low": 15760,
          "high": 20058
        },
        "30": {
          "low": 15760,
          "high": 20058
        }
      },
      "4": {
        "-5": {
          "low": 14550,
          "high": 18518
        },
        "0": {
          "low": 14550,
          "high": 18518
        },
        "5": {
          "low": 14550,
          "high": 18518
        },
        "10": {
          "low": 14575,
          "high": 18550
        },
        "15": {
          "low": 14572,
          "high": 18546
        },
        "20": {
          "low": 14572,
          "high": 18546
        },
        "25": {
          "low": 14572,
          "high": 18546
        },
        "30": {
          "low": 14572,
          "high": 18546
        }
      },
      "5": {
        "-5": {
          "low": 15172,
          "high": 19309
        },
        "0": {
          "low": 15172,
          "high": 19309
        },
        "5": {
          "low": 15172,
          "high": 19309
        },
        "10": {
          "low": 15196,
          "high": 19341
        },
        "15": {
          "low": 15191,
          "high": 19334
        },
        "20": {
          "low": 15191,
          "high": 19334
        },
        "25": {
          "low": 15191,
          "high": 19334
        },
        "30": {
          "low": 15191,
          "high": 19334
        }
      },
      "6": {
        "-5": {
          "low": 14987,
          "high": 19074
        },
        "0": {
          "low": 14987,
          "high": 19074
        },
        "5": {
          "low": 14987,
          "high": 19074
        },
        "10": {
          "low": 15011,
          "high": 19105
        },
        "15": {
          "low": 15006,
          "high": 19099
        },
        "20": {
          "low": 15006,
          "high": 19099
        },
        "25": {
          "low": 15006,
          "high": 19099
        },
        "30": {
          "low": 15006,
          "high": 19099
        }
      },
      "7": {
        "-5": {
          "low": 14978,
          "high": 19063
        },
        "0": {
          "low": 14978,
          "high": 19063
        },
        "5": {
          "low": 14978,
          "high": 19063
        },
        "10": {
          "low": 15003,
          "high": 19095
        },
        "15": {
          "low": 14998,
          "high": 19088
        },
        "20": {
          "low": 14998,
          "high": 19088
        },
        "25": {
          "low": 14998,
          "high": 19088
        },
        "30": {
          "low": 14998,
          "high": 19088
        }
      },
      "8": {
        "-5": {
          "low": 14950,
          "high": 19027
        },
        "0": {
          "low": 14950,
          "high": 19027
        },
        "5": {
          "low": 14950,
          "high": 19027
        },
        "10": {
          "low": 14974,
          "high": 19058
        },
        "15": {
          "low": 14971,
          "high": 19055
        },
        "20": {
          "low": 14971,
          "high": 19055
        },
        "25": {
          "low": 14971,
          "high": 19055
        },
        "30": {
          "low": 14971,
          "high": 19055
        }
      },
      "9": {
        "-5": {
          "low": 14853,
          "high": 18904
        },
        "0": {
          "low": 14853,
          "high": 18904
        },
        "5": {
          "low": 14853,
          "high": 18904
        },
        "10": {
          "low": 14878,
          "high": 18936
        },
        "15": {
          "low": 14875,
          "high": 18932
        },
        "20": {
          "low": 14875,
          "high": 18932
        },
        "25": {
          "low": 14875,
          "high": 18932
        },
        "30": {
          "low": 14875,
          "high": 18932
        }
      },
      "10": {
        "-5": {
          "low": 15018,
          "high": 19114
        },
        "0": {
          "low": 15018,
          "high": 19114
        },
        "5": {
          "low": 15018,
          "high": 19114
        },
        "10": {
          "low": 15043,
          "high": 19146
        },
        "15": {
          "low": 15038,
          "high": 19139
        },
        "20": {
          "low": 15038,
          "high": 19139
        },
        "25": {
          "low": 15038,
          "high": 19139
        },
        "30": {
          "low": 15038,
          "high": 19139
        }
      },
      "11": {
        "-5": {
          "low": 14538,
          "high": 18503
        },
        "0": {
          "low": 14538,
          "high": 18503
        },
        "5": {
          "low": 14538,
          "high": 18503
        },
        "10": {
          "low": 14563,
          "high": 18535
        },
        "15": {
          "low": 14563,
          "high": 18535
        },
        "20": {
          "low": 14563,
          "high": 18535
        },
        "25": {
          "low": 14563,
          "high": 18535
        },
        "30": {
          "low": 14563,
          "high": 18535
        }
      },
      "12": {
        "-5": {
          "low": 14547,
          "high": 18514
        },
        "0": {
          "low": 14547,
          "high": 18514
        },
        "5": {
          "low": 14547,
          "high": 18514
        },
        "10": {
          "low": 14571,
          "high": 18545
        },
        "15": {
          "low": 14571,
          "high": 18545
        },
        "20": {
          "low": 14571,
          "high": 18545
        },
        "25": {
          "low": 14571,
          "high": 18545
        },
        "30": {
          "low": 14571,
          "high": 18545
        }
      }
    }
  },
  "shap_features": {
    "global": [
      {
        "feature": "attendance_lag_1",
        "importance": 4591.0923
      },
      {
        "feature": "trust_historical_avg",
        "importance": 1479.2197
      },
      {
        "feature": "attendance_lag_2",
        "importance": 496.611
      },
      {
        "feature": "month",
        "importance": 264.5881
      },
      {
        "feature": "trust_size_encoded",
        "importance": 248.2085
      },
      {
        "feature": "num_school_holiday_weeks",
        "importance": 170.8714
      },
      {
        "feature": "yoy_change",
        "importance": 167.6486
      },
      {
        "feature": "is_winter",
        "importance": 153.8535
      },
      {
        "feature": "month_sin",
        "importance": 135.1081
      },
      {
        "feature": "flu_rate",
        "importance": 121.0929
      }
    ],
    "per_trust": [
      {
        "feature": "attendance_lag_1",
        "mean_shap": 3336.06,
        "mean_abs_shap": 3336.0571
      },
      {
        "feature": "trust_historical_avg",
        "mean_shap": 1374.95,
        "mean_abs_shap": 1374.9518
      },
      {
        "feature": "trust_size_encoded",
        "mean_shap": 332.88,
        "mean_abs_shap": 332.8752
      },
      {
        "feature": "year_numeric",
        "mean_shap": 127.6,
        "mean_abs_shap": 127.5976
      },
      {
        "feature": "month",
        "mean_shap": -92.71,
        "mean_abs_shap": 299.1349
      },
      {
        "feature": "yoy_change",
        "mean_shap": -66.55,
        "mean_abs_shap": 115.1414
      },
      {
        "feature": "attendance_lag_2",
        "mean_shap": 54.94,
        "mean_abs_shap": 66.7684
      },
      {
        "feature": "is_winter",
        "mean_shap": -38.62,
        "mean_abs_shap": 188.4363
      },
      {
        "feature": "attendance_lag_3",
        "mean_shap": 38.52,
        "mean_abs_shap": 38.5185
      },
      {
        "feature": "flu_rate",
        "mean_shap": 31.48,
        "mean_abs_shap": 131.397
      }
    ]
  },
  "anomalies": [
    {
      "year": 2020,
      "month": 10,
      "actual": 13015,
      "predicted": 14533,
      "deviation_pct": -10.4,
      "flag": "significantly_better"
    },
    {
      "year": 2020,
      "month": 11,
      "actual": 11527,
      "predicted": 12858,
      "deviation_pct": -10.3,
      "flag": "significantly_better"
    },
    {
      "year": 2021,
      "month": 10,
      "actual": 16535,
      "predicted": 17498,
      "deviation_pct": -5.5,
      "flag": "significantly_better"
    }
  ],
  "cluster": {
    "cluster_id": 0,
    "cluster_name": "Large teaching hospitals",
    "avg_attendance": 16076,
    "avg_breach_rate": 27.1
  }
}